{
  "author_name": "Captain Jupyter",
  "github_username": "{{ cookiecutter.author_name.lower().replace(' ', '') }}",
  "book_title": "My Book",
  "repo_name": "{{ cookiecutter.book_title.lower().replace(' ', '-') }}",
  "book_dir": "book",
  "book_short_description": "This cookiecutter creates a simple boilerplate for a Jupyter Book.",
  "version": "'0.1.0'",
  "open_source_license": [
    "MIT license",
    "BSD license",
    "ISC license",
    "Apache Software License 2.0",
    "GNU General Public License v3",
    "None"
  ],
  "include_ci": [
    "github",
    "gitlab",
    "no"
  ],
  "branch_name": [
    "master",
    "main"
  ]
}